idinn/__init__.py
idinn/demand.py
idinn/sourcing_model.py
idinn/dual_controller/__init__.py
idinn/dual_controller/base.py
idinn/dual_controller/capped_dual_index.py
idinn/dual_controller/dual_neural.py
idinn/dual_controller/dynamic_programming.py
idinn/single_controller/__init__.py
idinn/single_controller/base.py
idinn/single_controller/base_stock.py
idinn/single_controller/single_neural.py
idinn-0.2.0.post1.dist-info/METADATA
idinn-0.2.0.post1.dist-info/WHEEL
idinn-0.2.0.post1.dist-info/licenses/LICENSE
idinn-0.2.0.post1.dist-info/RECORD
