Metadata-Version: 2.4
Name: idinn
Version: 0.2.0.post1
Summary: Inventory dynamics–informed neural networks and other related controllers for solving single-sourcing and dual-sourcing problems.
Project-URL: Homepage, https://gitlab.com/ComputationalScience/idinn
Project-URL: Documentation, https://inventory-optimization.readthedocs.io
Project-URL: Issues, https://gitlab.com/ComputationalScience/idinn/-/issues
Author-email: Jiawei Li <sud.concept0x@icloud.com>, Thomas Asikis <thomas.asikis@uzh.ch>, Ioannis Fragkos <fragkos@rsm.nl>, Lucas Boettcher <l.boettcher@fs.de>
License: MIT License
License-File: LICENSE
Keywords: dynamic control,neural networks
Classifier: License :: OSI Approved :: MIT License
Classifier: Operating System :: OS Independent
Classifier: Programming Language :: Python :: 3
Requires-Python: >=3.10
Requires-Dist: matplotlib>=3.7.1
Requires-Dist: numba>=0.57
Requires-Dist: numpy>=2.0
Requires-Dist: tensorboard>=2.12
Requires-Dist: torch>=2.5
